LICENSE
MANIFEST.in
setup.py
openfire/__init__.py
openfire/base.py
openfire/exception.py
openfire/presence.py
openfire/user_service.py
python_openfire.egg-info/PKG-INFO
python_openfire.egg-info/SOURCES.txt
python_openfire.egg-info/dependency_links.txt
python_openfire.egg-info/not-zip-safe
python_openfire.egg-info/top_level.txt