Metadata-Version: 1.1
Name: python-openfire
Version: 0.2.3-beta
Summary: A python client for openfire’s api
Home-page: https://github.com/plazix/python-openfire
Author: Aleksandr Zorin (plazix)
Author-email: plazix@gmail.com
License: BSD License
Platform: UNKNOWN
Classifier: Development Status :: 3 - Alpha
Classifier: Intended Audience :: Developers
Classifier: License :: OSI Approved :: BSD License
Classifier: Operating System :: OS Independent
Classifier: Programming Language :: Python
